componenthierarchy/__init__.py
componenthierarchy/admin.py
componenthierarchy/model.py
componenthierarchy/ticket.py
componenthierarchy/htdocs/create_component_hierarchy.js
componenthierarchy/htdocs/css/component_hierarchy.css
TracComponentHierarchy-1.2.1.dist-info/COPYING
TracComponentHierarchy-1.2.1.dist-info/METADATA
TracComponentHierarchy-1.2.1.dist-info/WHEEL
TracComponentHierarchy-1.2.1.dist-info/entry_points.txt
TracComponentHierarchy-1.2.1.dist-info/top_level.txt
TracComponentHierarchy-1.2.1.dist-info/RECORD
